DEEP_causal
