Metadata-Version: 2.1
Name: DEEP-causal
Version: 0.0.22
Summary: DEEP_causal
Home-page: https://pypi.org/project/DEEP-causal/
Author: S.Zhang
Author-email: shisheng.zhang@mymail.unisa.edu.au
License: UNKNOWN
Platform: UNKNOWN
